smartlink_remote_restapi/__init__.py
smartlink_remote_restapi/smartlink_remote.py
smartlink_remote_restapi-0.0.30.dist-info/METADATA
smartlink_remote_restapi-0.0.30.dist-info/WHEEL
smartlink_remote_restapi-0.0.30.dist-info/top_level.txt
smartlink_remote_restapi-0.0.30.dist-info/RECORD
