Metadata-Version: 2.4
Name: smartlink-remote-restapi
Version: 0.0.30
Summary: PyPI Package for Circles smartlink-remote-restapi Python
Home-page: https://github.com/circles-zone/smartlink-remote-restapi-python-package
Author: Circles
Author-email: info@circlez.ai
Classifier: Programming Language :: Python :: 3
Classifier: License :: Other/Proprietary License
Classifier: Operating System :: OS Independent
Requires-Dist: requests
Requires-Dist: user-context-remote>=0.0.116
Requires-Dist: python-sdk-remote
Requires-Dist: logger-local
Requires-Dist: url-remote>=0.0.122
Requires-Dist: smartlink-local
Dynamic: author
Dynamic: author-email
Dynamic: classifier
Dynamic: description
Dynamic: description-content-type
Dynamic: home-page
Dynamic: requires-dist
Dynamic: summary
